geeker/__init__.py
geeker/__main__.py
geeker/cmdline.py
geeker/commands/__init__.py
geeker/functions/__init__.py
geeker/functions/mydata.py
geeker/functions/singleton.py
geeker/functions/timeout.py
geeker/functions/timeslimit.py
geeker/mylog/__init__.py
geeker/mylog/log_config.py
geeker/schedule/__init__.py
geeker/utils/__init__.py
geeker/utils/import_module.py
geeker-2.1.dist-info/LICENSE
geeker-2.1.dist-info/METADATA
geeker-2.1.dist-info/WHEEL
geeker-2.1.dist-info/entry_points.txt
geeker-2.1.dist-info/top_level.txt
geeker-2.1.dist-info/RECORD
