Metadata-Version: 2.1
Name: geeker
Version: 2.1
Summary: Some useful functions !
Home-page: https://github.com/4379711/functools_lyl
Author: liuyalong
Author-email: 4379711@qq.com
Maintainer: liuyalong
License: MIT License
Platform: all
Classifier: Development Status :: 4 - Beta
Classifier: Operating System :: OS Independent
Classifier: Intended Audience :: Developers
Classifier: License :: OSI Approved :: MIT License
Classifier: Programming Language :: Python :: 3.6
Classifier: Programming Language :: Python :: 3.7
Classifier: Programming Language :: Python :: 3.8
Classifier: Programming Language :: Python :: 3.9
Classifier: Topic :: Software Development :: Libraries
License-File: LICENSE
Requires-Dist: colorama
Requires-Dist: click
Requires-Dist: psutil
